purjo/Purjo.py
purjo/__init__.py
purjo/config.py
purjo/main.py
purjo/py.typed
purjo/runner.py
purjo/secrets.py
purjo/task.py
purjo/utils.py
purjo/data/Hello.py
purjo/data/RobotParser.py
purjo/data/hello.bpmn
purjo/data/hello.robot
purjo/data/tasks.py
purjo/data/template.bpmn
purjo/data/template.dmn
purjo/data/template.form
purjo-1.0b7.dist-info/METADATA
purjo-1.0b7.dist-info/WHEEL
purjo-1.0b7.dist-info/entry_points.txt
purjo-1.0b7.dist-info/licenses/LICENSE
purjo-1.0b7.dist-info/RECORD
